search_data_explorer/__init__.py
search_data_explorer/cli.py
search_data_explorer/search_data_explorer.py
search_data_explorer/streamlit_run.py
search_data_explorer/tde_streamlit/__init__.py
search_data_explorer/tde_streamlit/app.py
search_data_explorer/tde_streamlit/elements.py
search_data_explorer/tde_streamlit/widgets.py
search_data_explorer/tde_streamlit/components/2d_scatter.py
search_data_explorer/tde_streamlit/components/3d_scatter.py
search_data_explorer/tde_streamlit/components/__init__.py
search_data_explorer/tde_streamlit/components/filter.py
search_data_explorer/tde_streamlit/components/overview.py
search_data_explorer/tde_streamlit/components/parallel_categories.py
search_data_explorer/tde_streamlit/components/parallel_coordinates.py
search_data_explorer/tde_streamlit/components/scatter_matrix.py
search_data_explorer/tde_streamlit/components/widgets.py
search_data_explorer/tde_streamlit/plots/__init__.py
search_data_explorer/tde_streamlit/plots/plots.py
tests/__init__.py
search_data_explorer-0.4.2.dist-info/LICENSE
search_data_explorer-0.4.2.dist-info/METADATA
search_data_explorer-0.4.2.dist-info/WHEEL
search_data_explorer-0.4.2.dist-info/entry_points.txt
search_data_explorer-0.4.2.dist-info/top_level.txt
search_data_explorer-0.4.2.dist-info/RECORD
